middleware_client/__init__.py
middleware_client/middleware_client.py
scramjet_middleware_client-1.1.0.dist-info/METADATA
scramjet_middleware_client-1.1.0.dist-info/WHEEL
scramjet_middleware_client-1.1.0.dist-info/top_level.txt
scramjet_middleware_client-1.1.0.dist-info/RECORD
