Metadata-Version: 2.1
Name: scramjet-middleware-client
Version: 1.1.0
Home-page: https://github.com/scramjetorg/api-client-python/tree/main/middleware_client
Author: Scramjet
Author-email: open-source@scramjet.org
Requires-Python: >=3.9,<4.0
Requires-Dist: scramjet-client-utils (>=1.1.0)
Requires-Dist: scramjet-manager-client (>=1.1.0)
